[
  {
    "id": "days_of_conflict",
    "label": "Days of Conflict",
    "value": "12",
    "color": "red",
    "source": "Al Jazeera",
    "contested": false,
    "delta": "+1",
    "trend": "up",
    "lastUpdated": "2026-03-11T06:00:00.000Z"
  },
  {
    "id": "iran_killed",
    "label": "Iran Killed",
    "value": "2,600+",
    "color": "red",
    "source": "Al Jazeera / HRANA / Hengaw",
    "contested": true,
    "contestNote": "Iran claims 1,300+ civilians killed and ~10,000 civilian sites struck; Hengaw estimates 4,300+ total (incl. ~390 civilians) in first 10 days; HRANA estimates exceed 2,400 including 181+ children; internet blackout (~1% connectivity / 240hrs) severely limits verification. 5,000+ targets struck by US/Israel per CENTCOM.",
    "delta": "+200+",
    "trend": "up",
    "lastUpdated": "2026-03-11T06:00:00.000Z"
  },
  {
    "id": "us_killed",
    "label": "US Killed",
    "value": "8",
    "color": "amber",
    "source": "Pentagon",
    "contested": false,
    "delta": "+1",
    "trend": "up",
    "lastUpdated": "2026-03-10T12:00:00.000Z"
  },
  {
    "id": "israel_killed",
    "label": "Israel Killed",
    "value": "14+",
    "color": "amber",
    "source": "Israeli health authorities / Al Jazeera",
    "contested": false,
    "delta": "+2",
    "deltaNote": "2 civilians killed by Iranian cluster warhead missile in Yehud on March 10. Over 2,142 Israelis wounded in Iranian missile and drone attacks.",
    "trend": "up",
    "lastUpdated": "2026-03-10T12:00:00.000Z"
  },
  {
    "id": "gulf_killed",
    "label": "Gulf Region Killed",
    "value": "11+",
    "color": "red",
    "source": "Multiple Gulf defense ministries",
    "contested": false,
    "delta": "+7+",
    "trend": "up",
    "lastUpdated": "2026-03-10",
    "deltaNote": "Includes UAE (5, inc. 2 military), Bahrain (1), Kuwait (2), Saudi Arabia (2 foreign nationals), Oman (1). Gulf states reporting first direct civilian fatalities from Iranian strikes."
  },
  {
    "id": "lebanon_killed",
    "label": "Lebanon Killed",
    "value": "570+",
    "color": "amber",
    "source": "Lebanese health authorities / Lebanese gov disaster office",
    "contested": false,
    "delta": "+84+",
    "deltaNote": "Death toll includes 83+ children. 750,000 displaced. French emergency UN Security Council meeting called re: Lebanon.",
    "trend": "up",
    "lastUpdated": "2026-03-11T06:00:00.000Z"
  },
  {
    "id": "brent_crude",
    "label": "Brent Crude",
    "value": "~$90",
    "color": "red",
    "source": "Al Jazeera / Reuters / CNBC",
    "contested": false,
    "delta": "-$23",
    "trend": "down",
    "lastUpdated": "2026-03-11T06:00:00.000Z",
    "deltaNote": "Wild swings March 11: plunged 17% to below $80 on ceasefire speculation and IEA reserve release reports, then rebounded to ~$90 after US Energy Secretary Chris Wright briefly posted (then deleted) a claim of Navy tanker escort through Hormuz. IEA considering largest-ever strategic reserve release."
  },
  {
    "id": "flights_cancelled",
    "label": "Flights Cancelled",
    "value": "35,000+",
    "color": "blue",
    "source": "FlightAware / Al Jazeera",
    "contested": false,
    "delta": "+8,000",
    "deltaNote": "Dubai International Airport attacked by Iranian drones. Israel suspended all civilian air travel. UAE extended flight disruptions.",
    "trend": "up",
    "lastUpdated": "2026-03-10"
  },
  {
    "id": "countries_affected",
    "label": "Countries Affected",
    "value": "14+",
    "color": "blue",
    "source": "Al Jazeera / Reuters",
    "contested": false,
    "trend": "up",
    "lastUpdated": "2026-03-10",
    "delta": "+2",
    "deltaNote": "Iran, Israel, Lebanon, UAE, Bahrain, Kuwait, Qatar, Saudi Arabia, Oman, Iraq, Jordan, Azerbaijan, Turkey, Cyprus (UK RAF base). Pakistan also affected (consulate attack)."
  }
]
