{
  "operationName": "Operation Epic Fury / Roaring Lion",
  "dayCount": 7,
  "dateline": "DAY 7 — MARCH 6, 2026 — SITUATION REPORT",
  "heroHeadline": "US &amp; Israel Strike Iran,<br>Killing Supreme Leader <em>Khamenei</em>",
  "heroSubtitle": "Operation Epic Fury launched February 28 in the largest US military action in the Middle East since the 2003 Iraq invasion. The conflict has expanded to Lebanon, Iraq, and Gulf states with Iranian retaliatory strikes reaching Dubai, Doha, and Abu Dhabi.",
  "footerNote": "Data compiled from 80+ sources across 4 media poles as of March 4, 2026. All contested claims are marked. Multi-pole sourcing active.",
  "lastUpdated": "2026-03-06T05:57:54.619Z"
}
